{
  "id3:SA-01": {
    "name": "Ar Riyad",
    "ne_id": 1159310501,
    "population": 6777146,
    "wikidata_id": "Q1249255"
  },
  "id3:SA-02": {
    "name": "Makkah",
    "ne_id": 1159309311,
    "population": 0,
    "wikidata_id": "Q234167"
  },
  "id3:SA-03": {
    "name": "Al Madinah",
    "ne_id": 1159309295,
    "population": 0,
    "wikidata_id": "Q236027"
  },
  "id3:SA-04": {
    "name": "Ash Sharqiyah",
    "ne_id": 1159310437,
    "population": 4105780,
    "wikidata_id": "Q953508"
  },
  "id3:SA-05": {
    "name": "Al Quassim",
    "ne_id": 1159309297,
    "population": 1159438,
    "wikidata_id": "Q1105411"
  },
  "id3:SA-06": {
    "name": "Ha'il",
    "ne_id": 1159309299,
    "population": 0,
    "wikidata_id": "Q243656"
  },
  "id3:SA-07": {
    "name": "Tabuk",
    "ne_id": 1159309247,
    "population": 0,
    "wikidata_id": "Q1315953"
  },
  "id3:SA-08": {
    "name": "Al Hudud ash Shamaliyah",
    "ne_id": 1159309301,
    "population": 0,
    "wikidata_id": "Q201781"
  },
  "id3:SA-09": {
    "name": "Jizan",
    "ne_id": 1159309137,
    "population": 0,
    "wikidata_id": "Q269973"
  },
  "id3:SA-10": {
    "name": "Najran",
    "ne_id": 1159310499,
    "population": 0,
    "wikidata_id": "Q464718"
  },
  "id3:SA-11": {
    "name": "Al Bahah",
    "ne_id": 1159309307,
    "population": 0,
    "wikidata_id": "Q852774"
  },
  "id3:SA-12": {
    "name": "Al Jawf",
    "ne_id": 1159309303,
    "population": 0,
    "wikidata_id": "Q1471266"
  },
  "id3:SA-14": {
    "name": "`Asir",
    "ne_id": 1159309309,
    "population": 0,
    "wikidata_id": "Q779855"
  }
}