{
  "id3:SD-DE": {
    "name": "Central Darfur",
    "ne_id": 1159317839,
    "population": 0,
    "wikidata_id": "Q4116493"
  },
  "id3:SD-DN": {
    "name": "North Darfur",
    "ne_id": 1159309217,
    "population": 1583179,
    "wikidata_id": "Q688306"
  },
  "id3:SD-DS_1159309199": {
    "name": "Southern Darfur",
    "ne_id": 1159309199,
    "population": 0,
    "wikidata_id": "Q838778"
  },
  "id3:SD-DS_1159317841": {
    "name": "Eastern Darfur",
    "ne_id": 1159317841,
    "population": 0,
    "wikidata_id": "Q3545641"
  },
  "id3:SD-DW": {
    "name": "Western Darfur",
    "ne_id": 1159309195,
    "population": 0,
    "wikidata_id": "Q846331"
  },
  "id3:SD-GD": {
    "name": "Gedarif",
    "ne_id": 1159309205,
    "population": 0,
    "wikidata_id": "Q309478"
  },
  "id3:SD-GZ": {
    "name": "Gezira",
    "ne_id": 1159309203,
    "population": 0,
    "wikidata_id": "Q309469"
  },
  "id3:SD-KA": {
    "name": "Kassala",
    "ne_id": 1159309223,
    "population": 0,
    "wikidata_id": "Q954963"
  },
  "id3:SD-KH": {
    "name": "Khartoum",
    "ne_id": 1159309201,
    "population": 0,
    "wikidata_id": "Q310385"
  },
  "id3:SD-KN": {
    "name": "North Kordufan",
    "ne_id": 1159309221,
    "population": 0,
    "wikidata_id": "Q864093"
  },
  "id3:SD-KS": {
    "name": "South Kordufan",
    "ne_id": 1159309219,
    "population": 0,
    "wikidata_id": "Q465490"
  },
  "id3:SD-NB": {
    "name": "Blue Nile",
    "ne_id": 1159308277,
    "population": 0,
    "wikidata_id": "Q309489"
  },
  "id3:SD-NO": {
    "name": "Northern",
    "ne_id": 1159309209,
    "population": 0,
    "wikidata_id": "Q310118"
  },
  "id3:SD-NR": {
    "name": "River Nile",
    "ne_id": 1159309207,
    "population": 1472257,
    "wikidata_id": "Q849297"
  },
  "id3:SD-NW": {
    "name": "White Nile",
    "ne_id": 1159309211,
    "population": 0,
    "wikidata_id": "Q311371"
  },
  "id3:SD-RS": {
    "name": "Red Sea",
    "ne_id": 1159308281,
    "population": 0,
    "wikidata_id": "Q310120"
  },
  "id3:SD-SI": {
    "name": "Sennar",
    "ne_id": 1159309213,
    "population": 0,
    "wikidata_id": "Q865534"
  }
}